memory contrller/mem_ctrol.sv
`timescale 1ns/10ps
module memory (DataBus, MemWr, MemRd, Addr);
  inout [63:0] DataBus;
  input MemWr, MemRd;
  input [5:0] Addr;
  reg [63:0] datareg;
  reg [63:0] Mem [0:63];
 
  initial begin
    $readmemh ("input.txt", Mem);
    $display($time,"ns data write process done ");
  end
  
  always @ (MemWr or MemRd or Addr or datareg) begin
    	if (MemWr==1'b1 && MemRd==1'b0) begin
				Mem [Addr] =DataBus;
				datareg=64'hzzzzzzzzzzzzzzzz;
	 	end
	 	else if (MemRd==1'b1)	begin
        		datareg= Mem[Addr];
  
          $display($time,"ns data read Address-%h is %h\n",
                   Addr,datareg);
 
          $display($time,"ns data bus data is %h\n",DataBus);
	 	end
	 	else
			datareg=64'hzzzzzzzzzzzzzzzz;
   end
  assign DataBus = datareg;
  
endmodule

memory contrller/mem_ctrl_tb.v
`include "mem_ctrol.v"
module tb;
	reg MemWr;
	reg MemRd;
	reg [5:0] Addr;
	wire [63:0] DataBus;
	reg [63:0] Mem [0:63];

memory uut (
		.DataBus(DataBus),
  		.MemWr(MemWr),
  		.MemRd(MemRd),
		.Addr(Addr)
	 );

  initial begin

		MemWr = 0;
		MemRd = 0;
		Addr = 0;

		#20;
		MemRd = 1;
		MemWr = 0;
		Addr = 6'h00;
    	#10 $display(" Memory is read from Address %h----%h\n",Addr,DataBus);
      	#20;
		Addr = 6'h01;
		#10 $display(" Memory is read from Address %h---%h\n",Addr,DataBus);
		#20;
		Addr = 6'h02;
		#10 $display(" Memory is read from Address %h---%h\n",Addr,DataBus);
		#20;
		Addr = 6'h03;
		#10 $display(" Memory is read from Address %h---%h\n",Addr,DataBus);
		#20;
		Addr = 6'h04;
		#10 $display(" Memory is read from Address %h--%h\n",Addr,DataBus);
		#20;
		Addr = 6'h05;
		#10 $display(" Memory is read from Address %h--%h\n",Addr,DataBus);
		#20;
		Addr = 6'h06;
		#10 $display(" Memory is read from Address %h---%h\n",Addr,DataBus);
		#10 $finish;
  end
  initial 
    begin
      $dumpfile("dump.vcd");
      $dumpvars;          
   end
endmodule

memory contrller/dump.vcd
$date
	Wed Mar 23 13:22:30 2022
$end
$version
	Icarus Verilog
$end
$timescale
	10ps
$end
$scope module tb $end
$var wire 64 ! DataBus [63:0] $end
$var reg 6 " Addr [5:0] $end
$var reg 1 # MemRd $end
$var reg 1 $ MemWr $end
$scope module uut $end
$var wire 6 % Addr [5:0] $end
$var wire 64 & DataBus [63:0] $end
$var wire 1 ' MemRd $end
$var wire 1 ( MemWr $end
$var reg 64 ) datareg [63:0] $end
$upscope $end
$upscope $end
$enddefinitions $end
#0
$dumpvars
bz )
0(
0'
bz &
b0 %
0$
0#
b0 "
bz !
$end
#2000
b1111111111111111111111111111111111111111111111111111111111111111 )
b1111111111111111111111111111111111111111111111111111111111111111 !
b1111111111111111111111111111111111111111111111111111111111111111 &
1#
1'
#5000
b1110111011101110111011101110111011101110111011101110111011101110 )
b1110111011101110111011101110111011101110111011101110111011101110 !
b1110111011101110111011101110111011101110111011101110111011101110 &
b1 "
b1 %
#8000
b1011101110111011101110111011101110111011101110111011101110111011 )
b1011101110111011101110111011101110111011101110111011101110111011 !
b1011101110111011101110111011101110111011101110111011101110111011 &
b10 "
b10 %
#11000
b1010101010101010101010101010101010101010101010101010101010101010 )
b1010101010101010101010101010101010101010101010101010101010101010 !
b1010101010101010101010101010101010101010101010101010101010101010 &
b11 "
b11 %
#14000
b1001100110011001100110011001100110011001100110011001100110011001 )
b1001100110011001100110011001100110011001100110011001100110011001 !
b1001100110011001100110011001100110011001100110011001100110011001 &
b100 "
b100 %
#17000
b111011101110111011101110111011101110111011101110111011101110111 )
b111011101110111011101110111011101110111011101110111011101110111 !
b111011101110111011101110111011101110111011101110111011101110111 &
b101 "
b101 %
#20000
b10010000100100001001100110011 )
b10010000100100001001100110011 !
b10010000100100001001100110011 &
b110 "
b110 %
