FIFO Buffer/fifo_block.v
`timescale 1ns/1ps
module fifo(clk,reset,wr_en,rd_en,din,dout,full,empty);
  input clk,reset;
  input wr_en,rd_en;
  input [7:0]din;
  output [7:0]dout;
  output full,empty;
  
  reg [7:0]mem[0:15];//declaration of RAM
  wire clk,reset;
  wire wr_en,rd_en;
  wire [7:0]din;
  reg [7:0]dout;
  wire full,empty;
  reg [4:0]addr;
  integer i;
  assign full = (addr ==5'b10000) ? 1'b1 : 1'b0;
  assign empty = (addr ==5'b00000) ? 1'b1 : 1'b0;
  
  always@(posedge clk)
    begin
      if(reset)
        begin
        	addr = 4'b0000;
      		for(i=0;i<=15;i=i+1) 
        		mem[i] = 8'b0;
        end
      else if(wr_en | rd_en)//read or write
        begin
          if(wr_en && (!full))
            begin
            	mem[addr]=din;
            	addr = addr + 1;
            end
          else
            if(rd_en && (!empty))
              begin
                dout =mem[0];
                mem[0] = mem[1];
                mem[1] = mem[2];
                mem[2] = mem[3];
                mem[3] = mem[4];
                mem[4] = mem[5];
                mem[5] = mem[6];
                mem[6] = mem[7];
                mem[7] = mem[8];
                mem[8] = mem[9];
                mem[9] = mem[10];
                mem[10] = mem[11];
                mem[11] = mem[12];
                mem[12] = mem[13];
                mem[13] = mem[14];
                mem[14] = mem[15];
                mem[15] = 8'b0;
                   addr = addr - 1;         
                
              end
              
        end
      
    end
endmodule

FIFO Buffer/fifo_tb.v
`timescale 1ns/1ps
`include "fifo_block.v"
module test_fifo;//no ports
  reg clk,reset;
  reg wr_en,rd_en;
  reg [7:0]din;
  wire [7:0]dout;
  wire full,empty;
  
  fifo UUT(clk,reset,wr_en,rd_en,din,dout,full,empty); //instantiation

  initial begin
    clk =0;
    $display("clock initialize---------------");
      
  end
  
  task rst;
    begin
    #10  reset = 1;
      $display("reset initialize---------------");
    
      #20  reset = 0;//20 ns delay
         end
  endtask
  
  always #5 clk = ~clk;//T=10 ns, f=100Mhz
  
  task wr_rd_init;
    begin
    	wr_en =0;
      	rd_en =0;
      	din = 0;
      $display("write read initialize---------------");
    
    end
  endtask
  
  task write;
    input [7:0]wdata;
    begin
       @(posedge clk)
      begin
        wr_en =  1;
        din =  wdata;
      end
    end
  endtask
  
  task write16;
    begin
      write(8'hff);
      write(8'hfe);
      write(8'hfd);
      write(8'hfc);
      write(8'hfb);
      write(8'hfa);
      write(8'hf9);
      write(8'hf8);
      write(8'hf7);
      write(8'hf6);
      write(8'hf5);
      write(8'hf4);
      write(8'hf3);
      write(8'hf2);
      write(8'hf1);
      write(8'hf0);
      write(8'h11);
      
    end
  endtask
  
  task endwrite;
    begin
      wr_en = 0;
      din =  0;
    end
  endtask
  
  //read process
  task read;
    begin
      @(posedge clk)
      begin
        rd_en = 1;
      end
    end
  endtask
  
  task read16;
    begin
      read;read;read;read;
      read;read;read;read;
      read;read;read;read;
      read;read;read;read;
      
    end
  endtask
  
  task endread;
    begin
       @(posedge clk)
      begin
        rd_en = 0;
      end
    end
  endtask
  
  initial begin
    $display("start--- initialize---------------");
    
    rst;
    wr_rd_init;
    write16;
    endwrite;
    #2 read16;
    #10 endread;
    $display("stopped---------------");
    
    #10 $finish;//Stop the simulation
        
  end
  
  //waveform generation
  initial begin
    $dumpfile("dump.vcd");
    $dumpvars(1,test_fifo);
  end
endmodule

FIFO Buffer/dump.vcd
$date
	Wed Mar 23 13:30:35 2022
$end
$version
	Icarus Verilog
$end
$timescale
	1ps
$end
$scope module test_fifo $end
$var wire 8 ! dout [7:0] $end
$var wire 1 " empty $end
$var wire 1 # full $end
$var reg 1 $ clk $end
$var reg 8 % din [7:0] $end
$var reg 1 & rd_en $end
$var reg 1 ' reset $end
$var reg 1 ( wr_en $end
$upscope $end
$enddefinitions $end
#0
$dumpvars
x(
x'
x&
bx %
0$
x#
x"
bx !
$end
#5000
1$
#10000
0$
1'
#15000
0#
1"
1$
#20000
0$
#25000
1$
#30000
0$
b0 %
0&
0(
0'
#35000
0"
b11111111 %
1(
1$
#40000
0$
#45000
b11111110 %
1$
#50000
0$
#55000
b11111101 %
1$
#60000
0$
#65000
b11111100 %
1$
#70000
0$
#75000
b11111011 %
1$
#80000
0$
#85000
b11111010 %
1$
#90000
0$
#95000
b11111001 %
1$
#100000
0$
#105000
b11111000 %
1$
#110000
0$
#115000
b11110111 %
1$
#120000
0$
#125000
b11110110 %
1$
#130000
0$
#135000
b11110101 %
1$
#140000
0$
#145000
b11110100 %
1$
#150000
0$
#155000
b11110011 %
1$
#160000
0$
#165000
b11110010 %
1$
#170000
0$
#175000
b11110001 %
1$
#180000
0$
#185000
1#
b11110000 %
1$
#190000
0$
#195000
0(
b0 %
1$
#200000
0$
#205000
0#
b11111111 !
1&
1$
#210000
0$
#215000
b11111110 !
1$
#220000
0$
#225000
b11111101 !
1$
#230000
0$
#235000
b11111100 !
1$
#240000
0$
#245000
b11111011 !
1$
#250000
0$
#255000
b11111010 !
1$
#260000
0$
#265000
b11111001 !
1$
#270000
0$
#275000
b11111000 !
1$
#280000
0$
#285000
b11110111 !
1$
#290000
0$
#295000
b11110110 !
1$
#300000
0$
#305000
b11110101 !
1$
#310000
0$
#315000
b11110100 !
1$
#320000
0$
#325000
b11110011 !
1$
#330000
0$
#335000
b11110010 !
1$
#340000
0$
#345000
b11110001 !
1$
#350000
0$
#355000
1"
b11110000 !
1$
#360000
0$
#365000
0&
1$
